magpiem/__init__.py
magpiem/processing_cpp.cp310-win_amd64.pyd
magpiem/utils.py
magpiem/cpp/processing.cpp
magpiem/cpp/processing.hpp
magpiem/cpp/processing_extension.cpp
magpiem/cpp/processing_wrapper.cpp
magpiem/dash/__init__.py
magpiem/dash/callbacks_manager.py
magpiem/dash/dash_ui.py
magpiem/dash/layout.py
magpiem/dash/ui_callbacks.py
magpiem/io/README_emC_format.txt
magpiem/io/__init__.py
magpiem/io/io_utils.py
magpiem/io/mat_file_validation.py
magpiem/io/save_callbacks.py
magpiem/io/upload_callbacks.py
magpiem/plotting/__init__.py
magpiem/plotting/plot_cache.py
magpiem/plotting/plotting_callbacks.py
magpiem/plotting/plotting_utils.py
magpiem/processing/__init__.py
magpiem/processing/cpp_integration.py
magpiem/processing/processing_callbacks.py
magpiem/processing/processing_utils.py
magpiem/processing/classes/__init__.py
magpiem/processing/classes/cleaner.py
magpiem/processing/classes/particle.py
magpiem/processing/classes/tomogram.py
magpiem-1.0.1.dist-info/licenses/LICENSE
magpiem-1.0.1.dist-info/METADATA
magpiem-1.0.1.dist-info/WHEEL
magpiem-1.0.1.dist-info/entry_points.txt
magpiem-1.0.1.dist-info/top_level.txt
magpiem-1.0.1.dist-info/RECORD
