Metadata-Version: 2.4
Name: magpiem
Version: 1.0.1
Summary: Automated cleaning of sub-tomogram particle picking data
Author-email: Frank Nightingale <fnight128@gmail.com>
Project-URL: Homepage, https://github.com/fnight128/MagpiEM
Project-URL: Bug Tracker, https://github.com/fnight128/MagpiEM/issues
Classifier: Programming Language :: Python :: 3
Classifier: License :: OSI Approved :: MIT License
Classifier: Operating System :: OS Independent
Requires-Python: >=3.10
License-File: LICENSE
Requires-Dist: numpy
Requires-Dist: pandas
Requires-Dist: prettytable
Requires-Dist: scipy
Requires-Dist: plotly==5.15.0
Requires-Dist: pathlib
Requires-Dist: dash[diskcache]==2.15.0
Requires-Dist: dash_bootstrap_components==1.4.1
Requires-Dist: dash_bootstrap_templates==1.0.8
Requires-Dist: dash_extensions==1.0.1
Requires-Dist: dash_daq==0.5.0
Requires-Dist: flask==2.3.2
Requires-Dist: imodmodel
Requires-Dist: emfile
Requires-Dist: pyyaml
Requires-Dist: starfile
Requires-Dist: eulerangles
Dynamic: license-file
